README.rst
mipass.py
mipexpect.py
missh
setup.py
missh.egg-info/PKG-INFO
missh.egg-info/SOURCES.txt
missh.egg-info/dependency_links.txt
missh.egg-info/requires.txt
missh.egg-info/top_level.txt