Metadata-Version: 1.0
Name: missh
Version: 0.3.0
Summary: Minimalist Session Manager for SSH/SFTP
Home-page: https://github.com/LenxWei/MiSSH
Author: Lenx Wei
Author-email: lenx.wei@gmail.com
License: BSD
Keywords: ssh session manager
Platform: Independant
Classifier: Development Status :: 4 - Beta
Classifier: License :: OSI Approved :: BSD License
Classifier: Environment :: Console :: Curses
Classifier: Operating System :: POSIX
Classifier: Programming Language :: Python
Classifier: Intended Audience :: End Users/Desktop
Classifier: Topic :: Internet
